cythoncartesian/README.MD
cythoncartesian/__init__.py
cythoncartesian/requirements.txt
cythoncartesian/thirdparty.json
cythoncartesian-0.10.dist-info/LICENSE.rst
cythoncartesian-0.10.dist-info/METADATA
cythoncartesian-0.10.dist-info/WHEEL
cythoncartesian-0.10.dist-info/top_level.txt
cythoncartesian-0.10.dist-info/RECORD
