Metadata-Version: 2.1
Name: cythoncartesian
Version: 0.10
Summary: Cartesian Product - 6x faster than itertools.product - 10x less memory
Home-page: https://github.com/hansalemaos/cythoncartesian
Author: Johannes Fischer
Author-email: aulasparticularesdealemaosp@gmail.com
License: MIT
Keywords: cython,cartesian,product,itertools
Classifier: Development Status :: 4 - Beta
Classifier: Programming Language :: Python :: 3 :: Only
Classifier: Programming Language :: Python :: 3.10
Classifier: Topic :: Software Development :: Libraries :: Python Modules
Classifier: Topic :: Utilities
License-File: LICENSE.rst
Requires-Dist: Cython
Requires-Dist: numpy
